MANIFEST.in
setup.py
prosaic/__init__.py
prosaic/cfg.py
prosaic/commands.py
prosaic/dogma.py
prosaic/generation.py
prosaic/models.py
prosaic/nlp.py
prosaic/parsing.py
prosaic/util.py
prosaic.egg-info/PKG-INFO
prosaic.egg-info/SOURCES.txt
prosaic.egg-info/dependency_links.txt
prosaic.egg-info/entry_points.txt
prosaic.egg-info/requires.txt
prosaic.egg-info/top_level.txt
prosaic/templates/.example.template
prosaic/templates/couplet.json
prosaic/templates/fib.json
prosaic/templates/haiku.json
prosaic/templates/hard.json
prosaic/templates/sonnet.json