Metadata-Version: 1.1
Name: prosaic
Version: 6.1.1
Summary: prose scraper & cut-up poetry generator
Home-page: https://github.com/nathanielksmith/prosaic
Author: vilmibm shaksfrpease
Author-email: nks@lambdaphil.es
License: GPL
Keywords: poetry
Platform: UNKNOWN
Classifier: Topic :: Artistic Software
Classifier: License :: OSI Approved :: GNU General Public License v3 (GPLv3)
